MANIFEST.in
README.rst
setup.py
dubins/dubins.c
dubins/dubins.pyx
dubins.egg-info/PKG-INFO
dubins.egg-info/SOURCES.txt
dubins.egg-info/dependency_links.txt
dubins.egg-info/top_level.txt
dubins/include/dubins.h
dubins/src/dubins.c